pinecone_pulumi
