Metadata-Version: 2.4
Name: pinecone_pulumi
Version: 2.0.2
Summary: A Pulumi package for creating and managing Pinecone resources.
Home-page: https://www.pinecone.io
License: Apache-2.0
Project-URL: Repository, https://github.com/pinecone-io/pulumi-pinecone
Keywords: pulumi pinecone category/utility kind/native
Requires-Python: >=3.9
Requires-Dist: parver>=0.2.1
Requires-Dist: pulumi<4.0.0,>=3.0.0
Requires-Dist: semver>=2.8.1
Requires-Dist: typing-extensions<5,>=4.11; python_version < "3.11"
Dynamic: description
Dynamic: description-content-type
Dynamic: home-page
Dynamic: keywords
Dynamic: license
Dynamic: project-url
Dynamic: requires-dist
Dynamic: requires-python
Dynamic: summary
